{"YuwDkC0/FGhcFUM4iQJcJw==":"vkj33ahx_400x400-400x400.jpg","BwnYU+Iy+sjwGzyJ1riDbA==":"vkj33ahx_normal-48x48.jpg","76bzOENFHbdn5+XWMKtK3A==":"572483784-512x512.jpg","p3AdgTOapr3/8Y5vpNCWhQ==":"572484727-180x180.jpg","n8J0zq57w2GNyFeFrRVdVw==":"572486132-512x512.jpg","ODwZjjCbpckA1TeTqIfYTg==":"vkj33ahx_400x400-1-400x400.jpg","swHgVIU566rj2hAb74uphA==":"572484926-630x630.jpg","8c6bkRe3Z1lG9LGlZX8Epg==":"572486292-512x512.jpg","RVsTPnW0NhvZxJ+IP8VEjQ==":"572486418-512x512.jpg","Ul1sBkNin3TxEEaSgYX2cg==":"airshou-256x256.png","JNKLx7wa4r64En8Iob+NBg==":"q8dvdicon-175x175.jpg","N6l1nPbwSWI0DngNpcLlwQ==":"popcorntimeicon-178x178.png","Uf3zxO/DEiwHe0BDJd1hvQ==":"facebook-167x167.png","Hh0HiAWavpHv8aYYuKEKzA==":"%D8%AA%D9%86%D8%B2%D9%8A%D9%84-366x137.png","CRdKkJpfitns/oOpR/M3sQ==":"%D8%AA%D9%86%D8%B2%D9%8A%D9%84%20(1)-225x225.png","gvIUIKM474dCdSOXkmpoxQ==":"%D8%AA%D9%86%D8%B2%D9%8A%D9%84%20(2)-225x225.png","+7nHyIQPPR1T/ErBQmqDSw==":"%D8%AA%D9%86%D8%B2%D9%8A%D9%84%20(3)-248x203.png","jbO8aRLapdDeAVtDcvLPKg==":"%D8%AA%D9%86%D8%B2%D9%8A%D9%84-225x225.jpg","SQHQdB2aZr5NBZLjZAINEQ==":"images%20(1)-225x224.jpg","GgfO7eQBRdu1q2f0gTEM2Q==":"%D8%AA%D9%86%D8%B2%D9%8A%D9%84%20(4)-225x225.png","zs3yCUpBkXqsL/IQHljlCw==":"%D8%AA%D9%86%D8%B2%D9%8A%D9%84%20(1)-225x225.jpg","aRAOzj3B4bLJYWrpAVAcdw==":"%D8%AA%D9%86%D8%B2%D9%8A%D9%84-225x225.jpg","hu5HTOaOhPrjHP+O4ihCJA==":"512x512bb-512x512.jpg","13Lu8Wu0Nx8ApN8weuyEZg==":"ps-152x152.png","EzYAvAlXaXiFlNMDhf0cnw==":"457-350x350.png","IajUiDgWvZT2bDMI+xbMjw==":"227-175x175.png","g4QoT7dXT/CjkR46vkyQug==":"319-100x100.png","4Vk1ncFkQH9nGMhmE+C6BQ==":"75-512x512.png","PCGQelVD+jUUTW2g2/ItcQ==":"246-200x200.png","6qUVZHjWJanEBVvSTVJ5Jg==":"249-175x175.png","ha49Q5DZFLJYeTzKg3Od/w==":"250-175x175.png","RMod11aR/nLA6HlyV5kABw==":"276-350x350.png","cFR9KdUViRFdcCnE53J3yg==":"916-175x175.png","vnM1UEKEcKE1Erh6p6UySA==":"bbb-310x163.jpg","E4V6Qw7LWvIK9iRPC/b0sw==":"%D8%AA%D9%86%D8%B2%D9%8A%D9%84%20(6)-225x225.png","RIY1wKeW+VwhsxU+XO/LmQ==":"df0nbsxvaaiab8--300x168.jpg"}